sphinxcontrib_ghcontributors-0.1.0-py2.7-nspkg.pth
sphinxcontrib/ghcontributors.py
sphinxcontrib_ghcontributors-0.1.0.dist-info/METADATA
sphinxcontrib_ghcontributors-0.1.0.dist-info/RECORD
sphinxcontrib_ghcontributors-0.1.0.dist-info/WHEEL
sphinxcontrib_ghcontributors-0.1.0.dist-info/namespace_packages.txt
sphinxcontrib_ghcontributors-0.1.0.dist-info/top_level.txt
sphinxcontrib_ghcontributors-0.1.0.dist-info/zip-safe
